<workflow>
<wfName>DAAS_ENTRYPOINT_0_a</wfName>
	<branch>
		<tName1>emea_gw_0_a.1</tName1>
		<tName2>emea_udf_0_a.1</tName2>
		<fName></fName>
		<fRes>0</fRes>
		<fParams>
		</fParams>
	</branch>
	<branch>
		<tName1>emea_gw_0_a.1</tName1>
		<tName2>emea_qm_0_a.1</tName2>
		<fName></fName>
		<fRes>0</fRes>
		<fParams>
		</fParams>
	</branch>
	<branch>
		<tName1>emea_gw_0_a.1</tName1>
		<tName2>daas_ddlGw_a.1</tName2>
		<fName></fName>
		<fRes>0</fRes>
		<fParams>
		</fParams>
	</branch>
</workflow>
