<configparam>
	<ucname>delta_install_default</ucname>
	<override>TRTH_TAS_EQUITY.csv</override>
	<parameter>.daas.cfg.fwTargetDB</parameter>
	<description>Configuration parameter containing information on the location and parsing of csv files used by the client uploader process.
HDB - name of hdb process data is to be added to
tab - table name for upload of data
partedCol - name of column for data to be sorted on
whereClause - way to filter data to be written to disk
updateCols - used to update/add cols to raw data from csv file
dateParted - true if table is date partitioned
separator - file delimiter (e.g.  , for csv file)
</description>
	<validationAnalytic></validationAnalytic>
	<param>
		<index>0</index>
		<element>fatvar</element>
		<elementType>Symbol</elementType>
		<elementValue>TRTH_TAS.csv</elementValue>
	</param>
	<param>
		<index>0</index>
		<element>HDB</element>
		<elementType>Symbol</elementType>
		<elementValue></elementValue>
	</param>
	<param>
		<index>0</index>
		<element>tab</element>
		<elementType>Symbol</elementType>
		<elementValue>eqTrade</elementValue>
	</param>
	<param>
		<index>0</index>
		<element>partedCol</element>
		<elementType>String</elementType>
		<elementValue>`sym</elementValue>
	</param>
	<param>
		<index>0</index>
		<element>whereClause</element>
		<elementType>String</elementType>
		<elementValue>enlist(=;`type;($;enlist`;"Trade"))</elementValue>
	</param>
	<param>
		<index>0</index>
		<element>updateCols</element>
		<elementType>String</elementType>
		<elementValue>()</elementValue>
	</param>
	<param>
		<index>0</index>
		<element>dateParted</element>
		<elementType>Boolean</elementType>
		<elementValue>true</elementValue>
	</param>
	<param>
		<index>0</index>
		<element>separator</element>
		<elementType>Character</elementType>
		<elementValue>,</elementValue>
	</param>
	<param>
		<index>1</index>
		<element>fatvar</element>
		<elementType>Symbol</elementType>
		<elementValue>TRTH_TAS.csv</elementValue>
	</param>
	<param>
		<index>1</index>
		<element>HDB</element>
		<elementType>Symbol</elementType>
		<elementValue></elementValue>
	</param>
	<param>
		<index>1</index>
		<element>tab</element>
		<elementType>Symbol</elementType>
		<elementValue>eqQuote</elementValue>
	</param>
	<param>
		<index>1</index>
		<element>partedCol</element>
		<elementType>String</elementType>
		<elementValue>`sym</elementValue>
	</param>
	<param>
		<index>1</index>
		<element>whereClause</element>
		<elementType>String</elementType>
		<elementValue>enlist(=;`type;($;enlist`;"Quote"))</elementValue>
	</param>
	<param>
		<index>1</index>
		<element>updateCols</element>
		<elementType>String</elementType>
		<elementValue>()</elementValue>
	</param>
	<param>
		<index>1</index>
		<element>dateParted</element>
		<elementType>Boolean</elementType>
		<elementValue>true</elementValue>
	</param>
	<param>
		<index>1</index>
		<element>separator</element>
		<elementType>Character</elementType>
		<elementValue>,</elementValue>
	</param>
	<param>
		<index>2</index>
		<element>fatvar</element>
		<elementType>Symbol</elementType>
		<elementValue>TRTH_TAS.csv</elementValue>
	</param>
	<param>
		<index>2</index>
		<element>HDB</element>
		<elementType>Symbol</elementType>
		<elementValue></elementValue>
	</param>
	<param>
		<index>2</index>
		<element>tab</element>
		<elementType>Symbol</elementType>
		<elementValue>eqOpenClose</elementValue>
	</param>
	<param>
		<index>2</index>
		<element>partedCol</element>
		<elementType>String</elementType>
		<elementValue>`sym</elementValue>
	</param>
	<param>
		<index>2</index>
		<element>whereClause</element>
		<elementType>String</elementType>
		<elementValue>enlist(=;`type;($;enlist`;"Trade"))</elementValue>
	</param>
	<param>
		<index>2</index>
		<element>updateCols</element>
		<elementType>String</elementType>
		<elementValue>()</elementValue>
	</param>
	<param>
		<index>2</index>
		<element>dateParted</element>
		<elementType>Boolean</elementType>
		<elementValue>true</elementValue>
	</param>
	<param>
		<index>2</index>
		<element>separator</element>
		<elementType>Character</elementType>
		<elementValue>,</elementValue>
	</param>
	<param>
		<index>3</index>
		<element>fatvar</element>
		<elementType>Symbol</elementType>
		<elementValue>TRTH_TAS.csv</elementValue>
	</param>
	<param>
		<index>3</index>
		<element>HDB</element>
		<elementType>Symbol</elementType>
		<elementValue></elementValue>
	</param>
	<param>
		<index>3</index>
		<element>tab</element>
		<elementType>Symbol</elementType>
		<elementValue>ricInfo</elementValue>
	</param>
	<param>
		<index>3</index>
		<element>partedCol</element>
		<elementType>String</elementType>
		<elementValue>`sym</elementValue>
	</param>
	<param>
		<index>3</index>
		<element>whereClause</element>
		<elementType>String</elementType>
		<elementValue>()</elementValue>
	</param>
	<param>
		<index>3</index>
		<element>updateCols</element>
		<elementType>String</elementType>
		<elementValue>()</elementValue>
	</param>
	<param>
		<index>3</index>
		<element>dateParted</element>
		<elementType>Boolean</elementType>
		<elementValue>true</elementValue>
	</param>
	<param>
		<index>3</index>
		<element>separator</element>
		<elementType>Character</elementType>
		<elementValue>,</elementValue>
	</param>
	<param>
		<index>4</index>
		<element>fatvar</element>
		<elementType>Symbol</elementType>
		<elementValue>TRTH_TAS.csv</elementValue>
	</param>
	<param>
		<index>4</index>
		<element>HDB</element>
		<elementType>Symbol</elementType>
		<elementValue></elementValue>
	</param>
	<param>
		<index>4</index>
		<element>tab</element>
		<elementType>Symbol</elementType>
		<elementValue>eqCanCor</elementValue>
	</param>
	<param>
		<index>4</index>
		<element>partedCol</element>
		<elementType>String</elementType>
		<elementValue>`sym</elementValue>
	</param>
	<param>
		<index>4</index>
		<element>whereClause</element>
		<elementType>String</elementType>
		<elementValue>enlist(=;`type;($;enlist`;"Correction"))</elementValue>
	</param>
	<param>
		<index>4</index>
		<element>updateCols</element>
		<elementType>String</elementType>
		<elementValue>()</elementValue>
	</param>
	<param>
		<index>4</index>
		<element>dateParted</element>
		<elementType>Boolean</elementType>
		<elementValue>true</elementValue>
	</param>
	<param>
		<index>4</index>
		<element>separator</element>
		<elementType>Character</elementType>
		<elementValue>,</elementValue>
	</param>
	<param>
		<index>5</index>
		<element>fatvar</element>
		<elementType>Symbol</elementType>
		<elementValue>TRTH_TAS.csv</elementValue>
	</param>
	<param>
		<index>5</index>
		<element>HDB</element>
		<elementType>Symbol</elementType>
		<elementValue></elementValue>
	</param>
	<param>
		<index>5</index>
		<element>tab</element>
		<elementType>Symbol</elementType>
		<elementValue>auction</elementValue>
	</param>
	<param>
		<index>5</index>
		<element>partedCol</element>
		<elementType>String</elementType>
		<elementValue>`sym</elementValue>
	</param>
	<param>
		<index>5</index>
		<element>whereClause</element>
		<elementType>String</elementType>
		<elementValue>enlist(=;`type;($;enlist`;"Auction"))</elementValue>
	</param>
	<param>
		<index>5</index>
		<element>updateCols</element>
		<elementType>String</elementType>
		<elementValue>()</elementValue>
	</param>
	<param>
		<index>5</index>
		<element>dateParted</element>
		<elementType>Boolean</elementType>
		<elementValue>true</elementValue>
	</param>
	<param>
		<index>5</index>
		<element>separator</element>
		<elementType>Character</elementType>
		<elementValue>,</elementValue>
	</param>
</configparam>
