<configparam>
	<ucname>delta_install_default</ucname>
	<override>DEFAULT</override>
	<parameter>.daas.cfg.mifidAssetClass</parameter>
	<description></description>
	<validationAnalytic></validationAnalytic>
	<param>
		<index>0</index>
		<element>objectPermID</element>
		<elementType>Integer</elementType>
		<elementValue>1003442327</elementValue>
	</param>
	<param>
		<index>0</index>
		<element>assetClass</element>
		<elementType>Symbol</elementType>
		<elementValue>SHRS</elementValue>
	</param>
	<param>
		<index>1</index>
		<element>objectPermID</element>
		<elementType>Integer</elementType>
		<elementValue>1003442335</elementValue>
	</param>
	<param>
		<index>1</index>
		<element>assetClass</element>
		<elementType>Symbol</elementType>
		<elementValue>DPRS</elementValue>
	</param>
	<param>
		<index>2</index>
		<element>objectPermID</element>
		<elementType>Integer</elementType>
		<elementValue>1003442331</elementValue>
	</param>
	<param>
		<index>2</index>
		<element>assetClass</element>
		<elementType>Symbol</elementType>
		<elementValue>ETFS</elementValue>
	</param>
	<param>
		<index>3</index>
		<element>objectPermID</element>
		<elementType>Integer</elementType>
		<elementValue>1003442337</elementValue>
	</param>
	<param>
		<index>3</index>
		<element>assetClass</element>
		<elementType>Symbol</elementType>
		<elementValue>CRFT</elementValue>
	</param>
	<param>
		<index>4</index>
		<element>objectPermID</element>
		<elementType>Integer</elementType>
		<elementValue>1003442330</elementValue>
	</param>
	<param>
		<index>4</index>
		<element>assetClass</element>
		<elementType>Symbol</elementType>
		<elementValue>OTHE</elementValue>
	</param>
	<param>
		<index>5</index>
		<element>objectPermID</element>
		<elementType>Integer</elementType>
		<elementValue>1003476825</elementValue>
	</param>
	<param>
		<index>5</index>
		<element>assetClass</element>
		<elementType>Symbol</elementType>
		<elementValue>BOND</elementValue>
	</param>
	<param>
		<index>6</index>
		<element>objectPermID</element>
		<elementType>Integer</elementType>
		<elementValue>1003442328</elementValue>
	</param>
	<param>
		<index>6</index>
		<element>assetClass</element>
		<elementType>Symbol</elementType>
		<elementValue>SFPS</elementValue>
	</param>
	<param>
		<index>7</index>
		<element>objectPermID</element>
		<elementType>Integer</elementType>
		<elementValue>1003442329</elementValue>
	</param>
	<param>
		<index>7</index>
		<element>assetClass</element>
		<elementType>Symbol</elementType>
		<elementValue>SDRV</elementValue>
	</param>
	<param>
		<index>8</index>
		<element>objectPermID</element>
		<elementType>Integer</elementType>
		<elementValue>1003442332</elementValue>
	</param>
	<param>
		<index>8</index>
		<element>assetClass</element>
		<elementType>Symbol</elementType>
		<elementValue>EQDV</elementValue>
	</param>
	<param>
		<index>9</index>
		<element>objectPermID</element>
		<elementType>Integer</elementType>
		<elementValue>1003442338</elementValue>
	</param>
	<param>
		<index>9</index>
		<element>assetClass</element>
		<elementType>Symbol</elementType>
		<elementValue>CMDV</elementValue>
	</param>
	<param>
		<index>10</index>
		<element>objectPermID</element>
		<elementType>Integer</elementType>
		<elementValue>1003442336</elementValue>
	</param>
	<param>
		<index>10</index>
		<element>assetClass</element>
		<elementType>Symbol</elementType>
		<elementValue>CTDV</elementValue>
	</param>
	<param>
		<index>11</index>
		<element>objectPermID</element>
		<elementType>Integer</elementType>
		<elementValue>1003442339</elementValue>
	</param>
	<param>
		<index>11</index>
		<element>assetClass</element>
		<elementType>Symbol</elementType>
		<elementValue>CFDS</elementValue>
	</param>
	<param>
		<index>12</index>
		<element>objectPermID</element>
		<elementType>Integer</elementType>
		<elementValue>1003442333</elementValue>
	</param>
	<param>
		<index>12</index>
		<element>assetClass</element>
		<elementType>Symbol</elementType>
		<elementValue>EMAL</elementValue>
	</param>
	<param>
		<index>13</index>
		<element>objectPermID</element>
		<elementType>Integer</elementType>
		<elementValue>1003442334</elementValue>
	</param>
	<param>
		<index>13</index>
		<element>assetClass</element>
		<elementType>Symbol</elementType>
		<elementValue>EADV</elementValue>
	</param>
	<param>
		<index>14</index>
		<element>objectPermID</element>
		<elementType>Integer</elementType>
		<elementValue>1003476836</elementValue>
	</param>
	<param>
		<index>14</index>
		<element>assetClass</element>
		<elementType>Symbol</elementType>
		<elementValue>IRDV</elementValue>
	</param>
	<param>
		<index>15</index>
		<element>objectPermID</element>
		<elementType>Integer</elementType>
		<elementValue>1003476837</elementValue>
	</param>
	<param>
		<index>15</index>
		<element>assetClass</element>
		<elementType>Symbol</elementType>
		<elementValue>FXDV</elementValue>
	</param>
	<param>
		<index>16</index>
		<element>objectPermID</element>
		<elementType>Integer</elementType>
		<elementValue>1003476846</elementValue>
	</param>
	<param>
		<index>16</index>
		<element>assetClass</element>
		<elementType>Symbol</elementType>
		<elementValue>CRDV</elementValue>
	</param>
</configparam>
